gspread_sync/__init__.py
gspread_sync-0.0.3.dist-info/LICENSE
gspread_sync-0.0.3.dist-info/METADATA
gspread_sync-0.0.3.dist-info/WHEEL
gspread_sync-0.0.3.dist-info/top_level.txt
gspread_sync-0.0.3.dist-info/RECORD
