Metadata-Version: 2.1
Name: gspread-sync
Version: 0.0.3
Summary: google spreadsheet wrapper with multithread safety
Home-page: https://github.com/zenixls2/gspread_sync
Author: Zenix Huang
Author-email: zenixls2@gmail.com
License: Apache License 2.0
Keywords: spreadsheet google
Platform: any
Classifier: Development Status :: 5 - Production/Stable
Classifier: Environment :: Console
Classifier: Environment :: Web Environment
Classifier: Intended Audience :: Developers
Classifier: Intended Audience :: System Administrators
Classifier: License :: OSI Approved :: Apache Software License
Classifier: Programming Language :: Python :: 3
Classifier: Topic :: System :: Monitoring
Requires-Dist: google-api-python-client
Requires-Dist: httplib2
Requires-Dist: google-auth
Requires-Dist: google-auth-oauthlib
Requires-Dist: google-auth-httplib2
